cfiddle/Builder.py
cfiddle/CProtoParser.py
cfiddle/Code.py
cfiddle/Data.py
cfiddle/DebugInfo.py
cfiddle/Exceptions.py
cfiddle/ExternalRunner.py
cfiddle/GoProtoParser.py
cfiddle/Invoker.py
cfiddle/MakeBuilder.py
cfiddle/Parameters.py
cfiddle/ProtoParser.py
cfiddle/Runner.py
cfiddle/__init__.py
cfiddle/config.py
cfiddle/paths.py
cfiddle/source.py
cfiddle/util.py
cfiddle/CFG/__init__.py
cfiddle/CFG/cfg.py
cfiddle/Toolchain/Clang.py
cfiddle/Toolchain/Exceptions.py
cfiddle/Toolchain/GCC.py
cfiddle/Toolchain/Go.py
cfiddle/Toolchain/Registry.py
cfiddle/Toolchain/Toolchain.py
cfiddle/Toolchain/__init__.py
cfiddle/jupyter/__init__.py
cfiddle/jupyter/source.py
cfiddle/jupyter/util.py
cfiddle/perfcount/__init__.py
cfiddle/perfcount/perfcount.py
cfiddle/resources/include/DataSet.hpp
cfiddle/resources/include/PerfCounter.hpp
cfiddle/resources/include/PerfCounterDefs.hpp
cfiddle/resources/include/cfiddle.h
cfiddle/resources/include/cfiddle.hpp
cfiddle/resources/include/csv.hpp
cfiddle/resources/include/fastrand.h
cfiddle/resources/include/walltime.h
cfiddle/resources/libcfiddle/Makefile
cfiddle/resources/libcfiddle/cfiddle.cpp
cfiddle/resources/libcfiddle/export_perf_count_macros.cpp
cfiddle/resources/libcfiddle/build/arm-linux-gnueabi/cfiddle.d
cfiddle/resources/libcfiddle/build/arm-linux-gnueabi/cfiddle.ii
cfiddle/resources/libcfiddle/build/arm-linux-gnueabi/cfiddle.o
cfiddle/resources/libcfiddle/build/arm-linux-gnueabi/cfiddle.s
cfiddle/resources/libcfiddle/build/arm-linux-gnueabi/libcfiddle.so
cfiddle/resources/libcfiddle/build/powerpc-linux-gnu/cfiddle.d
cfiddle/resources/libcfiddle/build/powerpc-linux-gnu/cfiddle.ii
cfiddle/resources/libcfiddle/build/powerpc-linux-gnu/cfiddle.o
cfiddle/resources/libcfiddle/build/powerpc-linux-gnu/cfiddle.s
cfiddle/resources/libcfiddle/build/powerpc-linux-gnu/libcfiddle.so
cfiddle/resources/libcfiddle/build/x86_64-linux-gnu/cfiddle.d
cfiddle/resources/libcfiddle/build/x86_64-linux-gnu/cfiddle.ii
cfiddle-0.6.1.dist-info/LICENSE.txt
cfiddle-0.6.1.dist-info/METADATA
cfiddle-0.6.1.dist-info/WHEEL
cfiddle-0.6.1.dist-info/entry_points.txt
cfiddle-0.6.1.dist-info/top_level.txt
cfiddle-0.6.1.dist-info/RECORD
