Metadata-Version: 2.1
Name: cfiddle
Version: 0.6.1
Summary: CFiddle makes it easy to ask and answers questions about the compilation and execution of smallish programs written in compiled languages like C, C++, and Go.
Home-page: https://github.com/NVSL/cfiddle
Author: Steven Swanson
Author-email: swanson@cs.ucsd.edu
Classifier: Development Status :: 3 - Alpha
Classifier: Intended Audience :: Developers
Classifier: Intended Audience :: Education
Classifier: Topic :: Education
Classifier: Topic :: Education :: Computer Aided Instruction (CAI)
Classifier: Topic :: Software Development :: Compilers
Classifier: Framework :: Jupyter
Classifier: License :: OSI Approved :: MIT License
Classifier: Programming Language :: Python :: 3
Classifier: Programming Language :: Python :: 3.7
Classifier: Programming Language :: Python :: 3.8
Classifier: Programming Language :: Python :: 3.9
Classifier: Programming Language :: Python :: 3.10
Classifier: Programming Language :: Python :: 3.11
License-File: LICENSE.txt
Requires-Dist: pytest-cpp
Requires-Dist: pytest-xdist
Requires-Dist: click
Requires-Dist: pytest
Requires-Dist: pandas
Requires-Dist: IPython
Requires-Dist: nbmake
Requires-Dist: matplotlib
Requires-Dist: tqdm
Requires-Dist: ipywidgets
Requires-Dist: wheel
Requires-Dist: sphinx
Requires-Dist: twine
Requires-Dist: r2pipe
Requires-Dist: pydot
Requires-Dist: networkx
Requires-Dist: pyelftools
Requires-Dist: nbformat
